lab/lab2/lab2_hw/lab2.v
// pipelined fast multiplier
module mult_fast(
	output reg[7:0] P,  // product
	input[3:0] A, B,    // multiplicand and multiplier
	input clk		    // clock (posedge)
	);
	// stage 0 (input)
	reg[3:0] a_s0, b_s0;
	always @(posedge clk) begin
		a_s0 <= A;
		b_s0 <= B;
	end
	//$display("OAO, A=%b, B=%b.", A, B);
	// stage 1
	wire[3:0] pp0 = a_s0 & {4{b_s0[0]}}; // ignore the delays of AND gates
	wire[4:1] pp1 = a_s0 & {4{b_s0[1]}}; // ignore the delays of AND gates
	wire[5:2] pp2 = a_s0 & {4{b_s0[2]}}; // ignore the delays of AND gates
	wire[6:3] pp3 = a_s0 & {4{b_s0[3]}}; // ignore the delays of AND gates
	reg[5:1] sum1;
	always @(pp0, pp1)
		sum1[5:1] <= #7 pp0[3:1] + pp1[4:1]; // delay of the 4-bit adder
	reg[7:3] sum3;
	always @(pp2, pp3)
		sum3[7:3] <= #7 pp2[5:3] + pp3[6:3]; // delay of the 4-bit adder
	reg[5:0] sum1_s1;
	reg[7:2] sum3_s1;
	always @(posedge clk) begin
		sum1_s1 <= {sum1, pp0[0]};
		sum3_s1 <= {sum3, pp2[2]};
	end
	// stage 2 (outout)
	reg[7:2] sum2;
	always @(sum1_s1, sum3_s1)
		sum2[7:2] <= #8 sum1_s1[5:2] + sum3_s1[7:2]; // delay of the 6-bit adder
	always @(posedge clk) begin
		P <= {sum2, sum1_s1[1:0]};
	end
endmodule

// test bench
module mult_tb();
	// dump
	initial begin
		$dumpfile("lab2.vcd");
		$dumpvars(0, mult_tb);
	end
	// clock cycle = 10 ticks
	reg clock = 1;
	always
		#4 clock <= ~clock;
	// multiplier
	reg[3:0] A, B;
	wire[7:0] P;
	reg[7:0] P_ref;
	mult_fast mult(P, A, B, clock);
	always @(posedge clock)
		P_ref <= #16 A*B;
	// loop through all possible inputs
	integer i;
	initial begin
		#1;
		for(i=0; i<256; i=i+1) begin
			{A, B} <= i;
			#8;
//			$display("A=%b, B=%b.", A, B);
		end
		#21 $finish;
	end
	// check if the products are correct
	reg[3:0] A_old, B_old;
	always @(posedge clock) begin
		#1
		$display("P_ref: %b.", P_ref);
		$display("P    : %b.", P);
		if(P_ref!=P && i>=2) begin
			A_old = (i-2)/16;
			B_old = (i-2)%16;
			$display("Product is wrong when A=%b, B=%b.", A_old, B_old);
			$display("P_ref: %b.", P_ref);
			$display("P    : %b.", P);
			#9 $finish;
		end
	end
endmodule

lab/lab2/lab2_hw/lab2.vcd
$date
	Sat Jun  1 23:58:46 2019
$end
$version
	Icarus Verilog
$end
$timescale
	1s
$end
$scope module mult_tb $end
$var wire 8 ! P [7:0] $end
$var reg 4 " A [3:0] $end
$var reg 4 # A_old [3:0] $end
$var reg 4 $ B [3:0] $end
$var reg 4 % B_old [3:0] $end
$var reg 8 & P_ref [7:0] $end
$var reg 1 ' clock $end
$var integer 32 ( i [31:0] $end
$scope module mult $end
$var wire 4 ) A [3:0] $end
$var wire 4 * B [3:0] $end
$var wire 1 ' clk $end
$var wire 4 + pp0 [3:0] $end
$var wire 4 , pp1 [4:1] $end
$var wire 4 - pp2 [5:2] $end
$var wire 4 . pp3 [6:3] $end
$var reg 8 / P [7:0] $end
$var reg 4 0 a_s0 [3:0] $end
$var reg 4 1 b_s0 [3:0] $end
$var reg 5 2 sum1 [5:1] $end
$var reg 6 3 sum1_s1 [5:0] $end
$var reg 6 4 sum2 [7:2] $end
$var reg 5 5 sum3 [7:3] $end
$var reg 6 6 sum3_s1 [7:2] $end
$upscope $end
$upscope $end
$enddefinitions $end
#0
$dumpvars
bx 6
bx 5
bx 4
bx 3
bx 2
bx 1
bx 0
bx /
bx .
bx -
bx ,
bx +
bx *
bx )
bx (
1'
bx &
bx %
bx $
bx #
bx "
bx !
$end
#1
b0 "
b0 )
b0 $
b0 *
b0 (
#4
0'
#8
b0 .
b0 -
b0 ,
b0 +
b0 1
b0 0
1'
#9
b1 $
b1 *
b1 (
#12
0'
#15
b0 5
b0 2
#16
b1 1
b0 6
b0 3
1'
#17
b10 $
b10 *
b10 (
#20
0'
#24
b0 !
b0 /
b10 1
1'
b0 4
b0 &
#25
b11 $
b11 *
b11 (
#28
0'
#32
b11 1
1'
#33
b100 $
b100 *
b100 (
#36
0'
#40
b100 1
1'
#41
b101 $
b101 *
b101 (
#44
0'
#48
b101 1
1'
#49
b110 $
b110 *
b110 (
#52
0'
#56
b110 1
1'
#57
b111 $
b111 *
b111 (
#60
0'
#64
b111 1
1'
#65
b1000 $
b1000 *
b1000 (
#68
0'
#72
b1000 1
1'
#73
b1001 $
b1001 *
b1001 (
#76
0'
#80
b1001 1
1'
#81
b1010 $
b1010 *
b1010 (
#84
0'
#88
b1010 1
1'
#89
b1011 $
b1011 *
b1011 (
#92
0'
#96
b1011 1
1'
#97
b1100 $
b1100 *
b1100 (
#100
0'
#104
b1100 1
1'
#105
b1101 $
b1101 *
b1101 (
#108
0'
#112
b1101 1
1'
#113
b1110 $
b1110 *
b1110 (
#116
0'
#120
b1110 1
1'
#121
b1111 $
b1111 *
b1111 (
#124
0'
#128
b1111 1
1'
#129
b1 "
b1 )
b0 $
b0 *
b10000 (
#132
0'
#136
b0 .
b0 -
b0 ,
b0 +
b0 1
b1 0
1'
#137
b1 $
b1 *
b10001 (
#140
0'
#143
b0 5
b0 2
#144
b1 +
b1 1
1'
#145
b10 $
b10 *
b10010 (
#148
0'
#152
b0 +
b1 ,
b1 3
b10 1
1'
#153
b11 $
b11 *
b10011 (
#156
0'
#159
b1 2
#160
b1 +
b11 1
b10 3
b1 !
b1 /
1'
b1 &
#161
b100 $
b100 *
b10100 (
#164
0'
#168
b0 +
b0 ,
b1 -
b10 !
b10 /
b11 3
b100 1
1'
b10 &
#169
b101 $
b101 *
b10101 (
#172
0'
#175
b0 2
#176
b1 +
b101 1
b1 6
b0 3
b11 !
b11 /
1'
b11 &
#177
b110 $
b110 *
b10110 (
#180
0'
#184
b0 +
b1 ,
b100 !
b100 /
b1 3
b110 1
1'
b1 4
b100 &
#185
b111 $
b111 *
b10111 (
#188
0'
#191
b1 2
#192
b1 +
b111 1
b10 3
b101 !
b101 /
1'
b101 &
#193
b1000 $
b1000 *
b11000 (
#196
0'
#200
b0 +
b0 ,
b0 -
b1 .
b110 !
b110 /
b11 3
b1000 1
1'
b110 &
#201
b1001 $
b1001 *
b11001 (
#204
0'
#207
b0 2
b1 5
#208
b1 +
b1001 1
b10 6
b0 3
b111 !
b111 /
1'
b111 &
#209
b1010 $
b1010 *
b11010 (
#212
0'
#216
b0 +
b1 ,
b1000 !
b1000 /
b1 3
b1010 1
1'
b10 4
b1000 &
#217
b1011 $
b1011 *
b11011 (
#220
0'
#223
b1 2
#224
b1 +
b1011 1
b10 3
b1001 !
b1001 /
1'
b1001 &
#225
b1100 $
b1100 *
b11100 (
#228
0'
#232
b0 +
b0 ,
b1 -
b1010 !
b1010 /
b11 3
b1100 1
1'
b1010 &
#233
b1101 $
b1101 *
b11101 (
#236
0'
#239
b0 2
#240
b1 +
b1101 1
b11 6
b0 3
b1011 !
b1011 /
1'
b1011 &
#241
b1110 $
b1110 *
b11110 (
#244
0'
#248
b0 +
b1 ,
b1100 !
b1100 /
b1 3
b1110 1
1'
b11 4
b1100 &
#249
b1111 $
b1111 *
b11111 (
#252
0'
#255
b1 2
#256
b1 +
b1111 1
b10 3
b1101 !
b1101 /
1'
b1101 &
#257
b10 "
b10 )
b0 $
b0 *
b100000 (
#260
0'
#264
b0 .
b0 -
b0 ,
b0 +
b1110 !
b1110 /
b11 3
b0 1
b10 0
1'
b1110 &
#265
b1 $
b1 *
b100001 (
#268
0'
#271
b0 5
b0 2
#272
b10 +
b1 1
b0 6
b0 3
b1111 !
b1111 /
1'
b1111 &
#273
b10 $
b10 *
b100010 (
#276
0'
#279
b1 2
#280
b0 +
b10 ,
b0 !
b0 /
b10 3
b10 1
1'
b0 4
b0 &
#281
b11 $
b11 *
b100011 (
#284
0'
#287
b10 2
#288
b10 +
b11 1
b100 3
b10 !
b10 /
1'
b10 &
#289
b100 $
b100 *
b100100 (
#292
0'
#295
b11 2
#296
b0 +
b0 ,
b10 -
b100 !
b100 /
b110 3
b100 1
1'
b1 4
b100 &
#297
b101 $
b101 *
b100101 (
#300
0'
#303
b0 2
b1 5
#304
b10 +
b101 1
b10 6
b0 3
b110 !
b110 /
1'
b110 &
#305
b110 $
b110 *
b100110 (
#308
0'
#311
b1 2
#312
b0 +
b10 ,
b1000 !
b1000 /
b10 3
b110 1
1'
b10 4
b1000 &
#313
b111 $
b111 *
b100111 (
#316
0'
#319
b10 2
#320
b10 +
b111 1
b100 3
b1010 !
b1010 /
1'
b1010 &
#321
b1000 $
b1000 *
b101000 (
#324
0'
#327
b11 2
#328
b0 +
b0 ,
b0 -
b10 .
b1100 !
b1100 /
b110 3
b1000 1
1'
b11 4
b1100 &
#329
b1001 $
b1001 *
b101001 (
#332
0'
#335
b0 2
b10 5
#336
b10 +
b1001 1
b100 6
b0 3
b1110 !
b1110 /
1'
b1110 &
#337
b1010 $
b1010 *
b101010 (
#340
0'
#343
b1 2
#344
b0 +
b10 ,
b10000 !
b10000 /
b10 3
b1010 1
1'
b100 4
b10000 &
#345
b1011 $
b1011 *
b101011 (
#348
0'
#351
b10 2
#352
b10 +
b1011 1
b100 3
b10010 !
b10010 /
1'
b10010 &
#353
b1100 $
b1100 *
b101100 (
#356
0'
#359
b11 2
#360
b0 +
b0 ,
b10 -
b10100 !
b10100 /
b110 3
b1100 1
1'
b101 4
b10100 &
#361
b1101 $
b1101 *
b101101 (
#364
0'
#367
b0 2
b11 5
#368
b10 +
b1101 1
b110 6
b0 3
b10110 !
b10110 /
1'
b10110 &
#369
b1110 $
b1110 *
b101110 (
#372
0'
#375
b1 2
#376
b0 +
b10 ,
b11000 !
b11000 /
b10 3
b1110 1
1'
b110 4
b11000 &
#377
b1111 $
b1111 *
b101111 (
#380
0'
#383
b10 2
#384
b10 +
b1111 1
b100 3
b11010 !
b11010 /
1'
b11010 &
#385
b11 "
b11 )
b0 $
b0 *
b110000 (
#388
0'
#391
b11 2
#392
b0 .
b0 -
b0 ,
b0 +
b11100 !
b11100 /
b110 3
b0 1
b11 0
1'
b111 4
b11100 &
#393
b1 $
b1 *
b110001 (
#396
0'
#399
b0 5
b0 2
#400
b11 +
b1 1
b0 6
b0 3
b11110 !
b11110 /
1'
b11110 &
#401
b10 $
b10 *
b110010 (
#404
0'
#407
b1 2
#408
b0 +
b11 ,
b0 !
b0 /
b11 3
b10 1
1'
b0 4
b0 &
#409
b11 $
b11 *
b110011 (
#412
0'
#415
b11 2
#416
b11 +
b11 1
b110 3
b11 !
b11 /
1'
b11 &
#417
b100 $
b100 *
b110100 (
#420
0'
#423
b100 2
#424
b0 +
b0 ,
b11 -
b110 !
b110 /
b1001 3
b100 1
1'
b1 4
b110 &
#425
b101 $
b101 *
b110101 (
#428
0'
#431
b0 2
b1 5
#432
b11 +
b101 1
b11 6
b0 3
b1001 !
b1001 /
1'
b10 4
b1001 &
#433
b110 $
b110 *
b110110 (
#436
0'
#439
b1 2
#440
b0 +
b11 ,
b1100 !
b1100 /
b11 3
b110 1
1'
b11 4
b1100 &
#441
b111 $
b111 *
b110111 (
#444
0'
#447
b11 2
#448
b11 +
b111 1
b110 3
b1111 !
b1111 /
1'
b1111 &
#449
b1000 $
b1000 *
b111000 (
#452
0'
#455
b100 2
#456
b0 +
b0 ,
b0 -
b11 .
b10010 !
b10010 /
b1001 3
b1000 1
1'
b100 4
b10010 &
#457
b1001 $
b1001 *
b111001 (
#460
0'
#463
b0 2
b11 5
#464
b11 +
b1001 1
b110 6
b0 3
b10101 !
b10101 /
1'
b101 4
b10101 &
#465
b1010 $
b1010 *
b111010 (
#468
0'
#471
b1 2
#472
b0 +
b11 ,
b11000 !
b11000 /
b11 3
b1010 1
1'
b110 4
b11000 &
#473
b1011 $
b1011 *
b111011 (
#476
0'
#479
b11 2
#480
b11 +
b1011 1
b110 3
b11011 !
b11011 /
1'
b11011 &
#481
b1100 $
b1100 *
b111100 (
#484
0'
#487
b100 2
#488
b0 +
b0 ,
b11 -
b11110 !
b11110 /
b1001 3
b1100 1
1'
b111 4
b11110 &
#489
b1101 $
b1101 *
b111101 (
#492
0'
#495
b0 2
b100 5
#496
b11 +
b1101 1
b1001 6
b0 3
b100001 !
b100001 /
1'
b1000 4
b100001 &
#497
b1110 $
b1110 *
b111110 (
#500
0'
#503
b1 2
#504
b0 +
b11 ,
b100100 !
b100100 /
b11 3
b1110 1
1'
b1001 4
b100100 &
#505
b1111 $
b1111 *
b111111 (
#508
0'
#511
b11 2
#512
b11 +
b1111 1
b110 3
b100111 !
b100111 /
1'
b100111 &
#513
b100 "
b100 )
b0 $
b0 *
b1000000 (
#516
0'
#519
b100 2
#520
b0 .
b0 -
b0 ,
b0 +
b101010 !
b101010 /
b1001 3
b0 1
b100 0
1'
b1010 4
b101010 &
#521
b1 $
b1 *
b1000001 (
#524
0'
#527
b0 5
b0 2
#528
b100 +
b1 1
b0 6
b0 3
b101101 !
b101101 /
1'
b1011 4
b101101 &
#529
b10 $
b10 *
b1000010 (
#532
0'
#535
b10 2
#536
b0 +
b100 ,
b0 !
b0 /
b100 3
b10 1
1'
b0 4
b0 &
#537
b11 $
b11 *
b1000011 (
#540
0'
#543
b100 2
#544
b100 +
b11 1
b1000 3
b100 !
b100 /
1'
b1 4
b100 &
#545
b100 $
b100 *
b1000100 (
#548
0'
#551
b110 2
#552
b0 +
b0 ,
b100 -
b1000 !
b1000 /
b1100 3
b100 1
1'
b10 4
b1000 &
#553
b101 $
b101 *
b1000101 (
#556
0'
#559
b0 2
b10 5
#560
b100 +
b101 1
b100 6
b0 3
b1100 !
b1100 /
1'
b11 4
b1100 &
#561
b110 $
b110 *
b1000110 (
#564
0'
#567
b10 2
#568
b0 +
b100 ,
b10000 !
b10000 /
b100 3
b110 1
1'
b100 4
b10000 &
#569
b111 $
b111 *
b1000111 (
#572
0'
#575
b100 2
#576
b100 +
b111 1
b1000 3
b10100 !
b10100 /
1'
b101 4
b10100 &
#577
b1000 $
b1000 *
b1001000 (
#580
0'
#583
b110 2
#584
b0 +
b0 ,
b0 -
b100 .
b11000 !
b11000 /
b1100 3
b1000 1
1'
b110 4
b11000 &
#585
b1001 $
b1001 *
b1001001 (
#588
0'
#591
b0 2
b100 5
#592
b100 +
b1001 1
b1000 6
b0 3
b11100 !
b11100 /
1'
b111 4
b11100 &
#593
b1010 $
b1010 *
b1001010 (
#596
0'
#599
b10 2
#600
b0 +
b100 ,
b100000 !
b100000 /
b100 3
b1010 1
1'
b1000 4
b100000 &
#601
b1011 $
b1011 *
b1001011 (
#604
0'
#607
b100 2
#608
b100 +
b1011 1
b1000 3
b100100 !
b100100 /
1'
b1001 4
b100100 &
#609
b1100 $
b1100 *
b1001100 (
#612
0'
#615
b110 2
#616
b0 +
b0 ,
b100 -
b101000 !
b101000 /
b1100 3
b1100 1
1'
b1010 4
b101000 &
#617
b1101 $
b1101 *
b1001101 (
#620
0'
#623
b0 2
b110 5
#624
b100 +
b1101 1
b1100 6
b0 3
b101100 !
b101100 /
1'
b1011 4
b101100 &
#625
b1110 $
b1110 *
b1001110 (
#628
0'
#631
b10 2
#632
b0 +
b100 ,
b110000 !
b110000 /
b100 3
b1110 1
1'
b1100 4
b110000 &
#633
b1111 $
b1111 *
b1001111 (
#636
0'
#639
b100 2
#640
b100 +
b1111 1
b1000 3
b110100 !
b110100 /
1'
b1101 4
b110100 &
#641
b101 "
b101 )
b0 $
b0 *
b1010000 (
#644
0'
#647
b110 2
#648
b0 .
b0 -
b0 ,
b0 +
b111000 !
b111000 /
b1100 3
b0 1
b101 0
1'
b1110 4
b111000 &
#649
b1 $
b1 *
b1010001 (
#652
0'
#655
b0 5
b0 2
#656
b101 +
b1 1
b0 6
b0 3
b111100 !
b111100 /
1'
b1111 4
b111100 &
#657
b10 $
b10 *
b1010010 (
#660
0'
#663
b10 2
#664
b0 +
b101 ,
b0 !
b0 /
b101 3
b10 1
1'
b0 4
b0 &
#665
b11 $
b11 *
b1010011 (
#668
0'
#671
b101 2
#672
b101 +
b11 1
b1010 3
b101 !
b101 /
1'
b1 4
b101 &
#673
b100 $
b100 *
b1010100 (
#676
0'
#679
b111 2
#680
b0 +
b0 ,
b101 -
b1010 !
b1010 /
b1111 3
b100 1
1'
b10 4
b1010 &
#681
b101 $
b101 *
b1010101 (
#684
0'
#687
b0 2
b10 5
#688
b101 +
b101 1
b101 6
b0 3
b1111 !
b1111 /
1'
b11 4
b1111 &
#689
b110 $
b110 *
b1010110 (
#692
0'
#695
b10 2
#696
b0 +
b101 ,
b10100 !
b10100 /
b101 3
b110 1
1'
b101 4
b10100 &
#697
b111 $
b111 *
b1010111 (
#700
0'
#703
b101 2
#704
b101 +
b111 1
b1010 3
b11001 !
b11001 /
1'
b110 4
b11001 &
#705
b1000 $
b1000 *
b1011000 (
#708
0'
#711
b111 2
#712
b0 +
b0 ,
b0 -
b101 .
b11110 !
b11110 /
b1111 3
b1000 1
1'
b111 4
b11110 &
#713
b1001 $
b1001 *
b1011001 (
#716
0'
#719
b0 2
b101 5
#720
b101 +
b1001 1
b1010 6
b0 3
b100011 !
b100011 /
1'
b1000 4
b100011 &
#721
b1010 $
b1010 *
b1011010 (
#724
0'
#727
b10 2
#728
b0 +
b101 ,
b101000 !
b101000 /
b101 3
b1010 1
1'
b1010 4
b101000 &
#729
b1011 $
b1011 *
b1011011 (
#732
0'
#735
b101 2
#736
b101 +
b1011 1
b1010 3
b101101 !
b101101 /
1'
b1011 4
b101101 &
#737
b1100 $
b1100 *
b1011100 (
#740
0'
#743
b111 2
#744
b0 +
b0 ,
b101 -
b110010 !
b110010 /
b1111 3
b1100 1
1'
b1100 4
b110010 &
#745
b1101 $
b1101 *
b1011101 (
#748
0'
#751
b0 2
b111 5
#752
b101 +
b1101 1
b1111 6
b0 3
b110111 !
b110111 /
1'
b1101 4
b110111 &
#753
b1110 $
b1110 *
b1011110 (
#756
0'
#759
b10 2
#760
b0 +
b101 ,
b111100 !
b111100 /
b101 3
b1110 1
1'
b1111 4
b111100 &
#761
b1111 $
b1111 *
b1011111 (
#764
0'
#767
b101 2
#768
b101 +
b1111 1
b1010 3
b1000001 !
b1000001 /
1'
b10000 4
b1000001 &
#769
b110 "
b110 )
b0 $
b0 *
b1100000 (
#772
0'
#775
b111 2
#776
b0 .
b0 -
b0 ,
b0 +
b1000110 !
b1000110 /
b1111 3
b0 1
b110 0
1'
b10001 4
b1000110 &
#777
b1 $
b1 *
b1100001 (
#780
0'
#783
b0 5
b0 2
#784
b110 +
b1 1
b0 6
b0 3
b1001011 !
b1001011 /
1'
b10010 4
b1001011 &
#785
b10 $
b10 *
b1100010 (
#788
0'
#791
b11 2
#792
b0 +
b110 ,
b0 !
b0 /
b110 3
b10 1
1'
b0 4
b0 &
#793
b11 $
b11 *
b1100011 (
#796
0'
#799
b110 2
#800
b110 +
b11 1
b1100 3
b110 !
b110 /
1'
b1 4
b110 &
#801
b100 $
b100 *
b1100100 (
#804
0'
#807
b1001 2
#808
b0 +
b0 ,
b110 -
b1100 !
b1100 /
b10010 3
b100 1
1'
b11 4
b1100 &
#809
b101 $
b101 *
b1100101 (
#812
0'
#815
b0 2
b11 5
#816
b110 +
b101 1
b110 6
b0 3
b10010 !
b10010 /
1'
b100 4
b10010 &
#817
b110 $
b110 *
b1100110 (
#820
0'
#823
b11 2
#824
b0 +
b110 ,
b11000 !
b11000 /
b110 3
b110 1
1'
b110 4
b11000 &
#825
b111 $
b111 *
b1100111 (
#828
0'
#831
b110 2
#832
b110 +
b111 1
b1100 3
b11110 !
b11110 /
1'
b111 4
b11110 &
#833
b1000 $
b1000 *
b1101000 (
#836
0'
#839
b1001 2
#840
b0 +
b0 ,
b0 -
b110 .
b100100 !
b100100 /
b10010 3
b1000 1
1'
b1001 4
b100100 &
#841
b1001 $
b1001 *
b1101001 (
#844
0'
#847
b0 2
b110 5
#848
b110 +
b1001 1
b1100 6
b0 3
b101010 !
b101010 /
1'
b1010 4
b101010 &
#849
b1010 $
b1010 *
b1101010 (
#852
0'
#855
b11 2
#856
b0 +
b110 ,
b110000 !
b110000 /
b110 3
b1010 1
1'
b1100 4
b110000 &
#857
b1011 $
b1011 *
b1101011 (
#860
0'
#863
b110 2
#864
b110 +
b1011 1
b1100 3
b110110 !
b110110 /
1'
b1101 4
b110110 &
#865
b1100 $
b1100 *
b1101100 (
#868
0'
#871
b1001 2
#872
b0 +
b0 ,
b110 -
b111100 !
b111100 /
b10010 3
b1100 1
1'
b1111 4
b111100 &
#873
b1101 $
b1101 *
b1101101 (
#876
0'
#879
b0 2
b1001 5
#880
b110 +
b1101 1
b10010 6
b0 3
b1000010 !
b1000010 /
1'
b10000 4
b1000010 &
#881
b1110 $
b1110 *
b1101110 (
#884
0'
#887
b11 2
#888
b0 +
b110 ,
b1001000 !
b1001000 /
b110 3
b1110 1
1'
b10010 4
b1001000 &
#889
b1111 $
b1111 *
b1101111 (
#892
0'
#895
b110 2
#896
b110 +
b1111 1
b1100 3
b1001110 !
b1001110 /
1'
b10011 4
b1001110 &
#897
b111 "
b111 )
b0 $
b0 *
b1110000 (
#900
0'
#903
b1001 2
#904
b0 .
b0 -
b0 ,
b0 +
b1010100 !
b1010100 /
b10010 3
b0 1
b111 0
1'
b10101 4
b1010100 &
#905
b1 $
b1 *
b1110001 (
#908
0'
#911
b0 5
b0 2
#912
b111 +
b1 1
b0 6
b0 3
b1011010 !
b1011010 /
1'
b10110 4
b1011010 &
#913
b10 $
b10 *
b1110010 (
#916
0'
#919
b11 2
#920
b0 +
b111 ,
b0 !
b0 /
b111 3
b10 1
1'
b0 4
b0 &
#921
b11 $
b11 *
b1110011 (
#924
0'
#927
b111 2
#928
b111 +
b11 1
b1110 3
b111 !
b111 /
1'
b1 4
b111 &
#929
b100 $
b100 *
b1110100 (
#932
0'
#935
b1010 2
#936
b0 +
b0 ,
b111 -
b1110 !
b1110 /
b10101 3
b100 1
1'
b11 4
b1110 &
#937
b101 $
b101 *
b1110101 (
#940
0'
#943
b0 2
b11 5
#944
b111 +
b101 1
b111 6
b0 3
b10101 !
b10101 /
1'
b101 4
b10101 &
#945
b110 $
b110 *
b1110110 (
#948
0'
#951
b11 2
#952
b0 +
b111 ,
b11100 !
b11100 /
b111 3
b110 1
1'
b111 4
b11100 &
#953
b111 $
b111 *
b1110111 (
#956
0'
#959
b111 2
#960
b111 +
b111 1
b1110 3
b100011 !
b100011 /
1'
b1000 4
b100011 &
#961
b1000 $
b1000 *
b1111000 (
#964
0'
#967
b1010 2
#968
b0 +
b0 ,
b0 -
b111 .
b101010 !
b101010 /
b10101 3
b1000 1
1'
b1010 4
b101010 &
#969
b1001 $
b1001 *
b1111001 (
#972
0'
#975
b0 2
b111 5
#976
b111 +
b1001 1
b1110 6
b0 3
b110001 !
b110001 /
1'
b1100 4
b110001 &
#977
b1010 $
b1010 *
b1111010 (
#980
0'
#983
b11 2
#984
b0 +
b111 ,
b111000 !
b111000 /
b111 3
b1010 1
1'
b1110 4
b111000 &
#985
b1011 $
b1011 *
b1111011 (
#988
0'
#991
b111 2
#992
b111 +
b1011 1
b1110 3
b111111 !
b111111 /
1'
b1111 4
b111111 &
#993
b1100 $
b1100 *
b1111100 (
#996
0'
#999
b1010 2
#1000
b0 +
b0 ,
b111 -
b1000110 !
b1000110 /
b10101 3
b1100 1
1'
b10001 4
b1000110 &
#1001
b1101 $
b1101 *
b1111101 (
#1004
0'
#1007
b0 2
b1010 5
#1008
b111 +
b1101 1
b10101 6
b0 3
b1001101 !
b1001101 /
1'
b10011 4
b1001101 &
#1009
b1110 $
b1110 *
b1111110 (
#1012
0'
#1015
b11 2
#1016
b0 +
b111 ,
b1010100 !
b1010100 /
b111 3
b1110 1
1'
b10101 4
b1010100 &
#1017
b1111 $
b1111 *
b1111111 (
#1020
0'
#1023
b111 2
#1024
b111 +
b1111 1
b1110 3
b1011011 !
b1011011 /
1'
b10110 4
b1011011 &
#1025
b1000 "
b1000 )
b0 $
b0 *
b10000000 (
#1028
0'
#1031
b1010 2
#1032
b0 .
b0 -
b0 ,
b0 +
b1100010 !
b1100010 /
b10101 3
b0 1
b1000 0
1'
b11000 4
b1100010 &
#1033
b1 $
b1 *
b10000001 (
#1036
0'
#1039
b0 5
b0 2
#1040
b1000 +
b1 1
b0 6
b0 3
b1101001 !
b1101001 /
1'
b11010 4
b1101001 &
#1041
b10 $
b10 *
b10000010 (
#1044
0'
#1047
b100 2
#1048
b0 +
b1000 ,
b0 !
b0 /
b1000 3
b10 1
1'
b0 4
b0 &
#1049
b11 $
b11 *
b10000011 (
#1052
0'
#1055
b1000 2
#1056
b1000 +
b11 1
b10000 3
b1000 !
b1000 /
1'
b10 4
b1000 &
#1057
b100 $
b100 *
b10000100 (
#1060
0'
#1063
b1100 2
#1064
b0 +
b0 ,
b1000 -
b10000 !
b10000 /
b11000 3
b100 1
1'
b100 4
b10000 &
#1065
b101 $
b101 *
b10000101 (
#1068
0'
#1071
b0 2
b100 5
#1072
b1000 +
b101 1
b1000 6
b0 3
b11000 !
b11000 /
1'
b110 4
b11000 &
#1073
b110 $
b110 *
b10000110 (
#1076
0'
#1079
b100 2
#1080
b0 +
b1000 ,
b100000 !
b100000 /
b1000 3
b110 1
1'
b1000 4
b100000 &
#1081
b111 $
b111 *
b10000111 (
#1084
0'
#1087
b1000 2
#1088
b1000 +
b111 1
b10000 3
b101000 !
b101000 /
1'
b1010 4
b101000 &
#1089
b1000 $
b1000 *
b10001000 (
#1092
0'
#1095
b1100 2
#1096
b0 +
b0 ,
b0 -
b1000 .
b110000 !
b110000 /
b11000 3
b1000 1
1'
b1100 4
b110000 &
#1097
b1001 $
b1001 *
b10001001 (
#1100
0'
#1103
b0 2
b1000 5
#1104
b1000 +
b1001 1
b10000 6
b0 3
b111000 !
b111000 /
1'
b1110 4
b111000 &
#1105
b1010 $
b1010 *
b10001010 (
#1108
0'
#1111
b100 2
#1112
b0 +
b1000 ,
b1000000 !
b1000000 /
b1000 3
b1010 1
1'
b10000 4
b1000000 &
#1113
b1011 $
b1011 *
b10001011 (
#1116
0'
#1119
b1000 2
#1120
b1000 +
b1011 1
b10000 3
b1001000 !
b1001000 /
1'
b10010 4
b1001000 &
#1121
b1100 $
b1100 *
b10001100 (
#1124
0'
#1127
b1100 2
#1128
b0 +
b0 ,
b1000 -
b1010000 !
b1010000 /
b11000 3
b1100 1
1'
b10100 4
b1010000 &
#1129
b1101 $
b1101 *
b10001101 (
#1132
0'
#1135
b0 2
b1100 5
#1136
b1000 +
b1101 1
b11000 6
b0 3
b1011000 !
b1011000 /
1'
b10110 4
b1011000 &
#1137
b1110 $
b1110 *
b10001110 (
#1140
0'
#1143
b100 2
#1144
b0 +
b1000 ,
b1100000 !
b1100000 /
b1000 3
b1110 1
1'
b11000 4
b1100000 &
#1145
b1111 $
b1111 *
b10001111 (
#1148
0'
#1151
b1000 2
#1152
b1000 +
b1111 1
b10000 3
b1101000 !
b1101000 /
1'
b11010 4
b1101000 &
#1153
b1001 "
b1001 )
b0 $
b0 *
b10010000 (
#1156
0'
#1159
b1100 2
#1160
b0 .
b0 -
b0 ,
b0 +
b1110000 !
b1110000 /
b11000 3
b0 1
b1001 0
1'
b11100 4
b1110000 &
#1161
b1 $
b1 *
b10010001 (
#1164
0'
#1167
b0 5
b0 2
#1168
b1001 +
b1 1
b0 6
b0 3
b1111000 !
b1111000 /
1'
b11110 4
b1111000 &
#1169
b10 $
b10 *
b10010010 (
#1172
0'
#1175
b100 2
#1176
b0 +
b1001 ,
b0 !
b0 /
b1001 3
b10 1
1'
b0 4
b0 &
#1177
b11 $
b11 *
b10010011 (
#1180
0'
#1183
b1001 2
#1184
b1001 +
b11 1
b10010 3
b1001 !
b1001 /
1'
b10 4
b1001 &
#1185
b100 $
b100 *
b10010100 (
#1188
0'
#1191
b1101 2
#1192
b0 +
b0 ,
b1001 -
b10010 !
b10010 /
b11011 3
b100 1
1'
b100 4
b10010 &
#1193
b101 $
b101 *
b10010101 (
#1196
0'
#1199
b0 2
b100 5
#1200
b1001 +
b101 1
b1001 6
b0 3
b11011 !
b11011 /
1'
b110 4
b11011 &
#1201
b110 $
b110 *
b10010110 (
#1204
0'
#1207
b100 2
#1208
b0 +
b1001 ,
b100100 !
b100100 /
b1001 3
b110 1
1'
b1001 4
b100100 &
#1209
b111 $
b111 *
b10010111 (
#1212
0'
#1215
b1001 2
#1216
b1001 +
b111 1
b10010 3
b101101 !
b101101 /
1'
b1011 4
b101101 &
#1217
b1000 $
b1000 *
b10011000 (
#1220
0'
#1223
b1101 2
#1224
b0 +
b0 ,
b0 -
b1001 .
b110110 !
b110110 /
b11011 3
b1000 1
1'
b1101 4
b110110 &
#1225
b1001 $
b1001 *
b10011001 (
#1228
0'
#1231
b0 2
b1001 5
#1232
b1001 +
b1001 1
b10010 6
b0 3
b111111 !
b111111 /
1'
b1111 4
b111111 &
#1233
b1010 $
b1010 *
b10011010 (
#1236
0'
#1239
b100 2
#1240
b0 +
b1001 ,
b1001000 !
b1001000 /
b1001 3
b1010 1
1'
b10010 4
b1001000 &
#1241
b1011 $
b1011 *
b10011011 (
#1244
0'
#1247
b1001 2
#1248
b1001 +
b1011 1
b10010 3
b1010001 !
b1010001 /
1'
b10100 4
b1010001 &
#1249
b1100 $
b1100 *
b10011100 (
#1252
0'
#1255
b1101 2
#1256
b0 +
b0 ,
b1001 -
b1011010 !
b1011010 /
b11011 3
b1100 1
1'
b10110 4
b1011010 &
#1257
b1101 $
b1101 *
b10011101 (
